[
        {"id": "1", "name": "Vitrine location immobilière", "type": "web","typeFull": "Web", "img": "vitrine-final.jpg" },
        {"id": "2", "name":  "Portfolio et CV", "type": "web","typeFull": "Web", "img": "web2.jpg" },
        {"id": "3", "name":  "Data science 1", "type": "ds", "typeFull": "Data science", "img": "ds1-final.jpg"},
        {"id": "4", "name":  "Data science 2", "type": "ds","typeFull": "Data science", "img": "ds2-final.jpg" },
        {"id": "5", "name":  "Iris", "type": "ds","typeFull": "Data science", "img": "iris-final.jpg" }
]